{
  "_class": "artboard",
  "backgroundColor": {
    "_class": "color",
    "alpha": 1,
    "blue": 1,
    "do_objectID": "ACFD9F7C-0A33-446C-96D6-8D4E50E4FB0F",
    "green": 1,
    "red": 1
  },
  "booleanOperation": -1,
  "do_objectID": "1C0F82CF-2688-42D6-8F38-4EE30BE3C49E",
  "exportOptions": {
    "_class": "exportOptions",
    "do_objectID": "2C41BA27-B354-487D-BC16-6681F36271A1",
    "exportFormats": [
    ],
    "includedLayerIds": [
    ],
    "layerOptions": 0,
    "shouldTrim": false
  },
  "frame": {
    "_class": "rect",
    "constrainProportions": false,
    "do_objectID": "ADDEE838-5F36-4E40-A155-D7293D917C40",
    "height": 1024,
    "width": 1440,
    "x": -515,
    "y": -431
  },
  "hasBackgroundColor": true,
  "hasClickThrough": false,
  "horizontalRulerData": {
    "_class": "rulerData",
    "base": 0,
    "do_objectID": "46703E60-DBC0-4593-A047-19E4195C913C",
    "guides": [
    ]
  },
  "includeBackgroundColorInExport": true,
  "includeInCloudUpload": true,
  "isFixedToViewport": false,
  "isFlippedHorizontal": false,
  "isFlippedVertical": false,
  "isFlowHome": false,
  "isLocked": false,
  "isVisible": true,
  "layerListExpandedType": 1,
  "layers": [
    {
      "class": "group",
      "id": "2955D40A-06CC-4198-95CB-D0EC02869483"
    },
    {
      "class": "group",
      "id": "EE79DA13-8912-4E9E-9F40-6FE2B1F05765"
    },
    {
      "class": "text",
      "id": "A07B0665-1C8D-49FE-9F54-4EEE8D7EFF3B"
    },
    {
      "class": "text",
      "id": "47F947B2-5DE6-4238-ADE4-DCD23F5388C6"
    },
    {
      "class": "text",
      "id": "DCB41844-BC72-4749-85D3-DA2F0F232AD6"
    }
  ],
  "name": "Ant Design Welcome",
  "nameIsFixed": true,
  "presetDictionary": {
    "allowResizedMatching": 0,
    "height": 1024,
    "name": "Desktop HD",
    "offersLandscapeVariant": 0,
    "width": 1440
  },
  "resizesContent": false,
  "resizingConstraint": 63,
  "resizingType": 0,
  "rotation": 0,
  "shouldBreakMaskChain": true,
  "style": {
    "_class": "style",
    "do_objectID": "5A41E944-8C85-4598-9A55-5C4E86F90F89",
    "endMarkerType": 0,
    "miterLimit": 10,
    "startMarkerType": 0,
    "windingRule": 1
  },
  "verticalRulerData": {
    "_class": "rulerData",
    "base": 0,
    "do_objectID": "9FCBBCCE-6A22-443B-AD3D-E3181132AE76",
    "guides": [
    ]
  }
}