{
  "_class": "group",
  "booleanOperation": 0,
  "do_objectID": "D0F5D964-DBF5-4F41-A916-F3A8646FB039",
  "exportOptions": {
    "_class": "exportOptions",
    "do_objectID": "F0D707B5-3052-44F9-8651-5CEBCCAB74D6",
    "exportFormats": [
    ],
    "includedLayerIds": [
    ],
    "layerOptions": 0,
    "shouldTrim": false
  },
  "frame": {
    "_class": "rect",
    "constrainProportions": false,
    "do_objectID": "4DDB4942-8BF9-4637-AED7-F913A578AC4E",
    "height": 273,
    "width": 720,
    "x": 120,
    "y": 570
  },
  "hasClickThrough": false,
  "isFixedToViewport": false,
  "isFlippedHorizontal": false,
  "isFlippedVertical": false,
  "isLocked": false,
  "isVisible": true,
  "layerListExpandedType": 0,
  "layers": [
    {
      "class": "text",
      "id": "B72DCB6D-E9F1-4927-ACAE-E72E2E461572"
    },
    {
      "class": "shapeGroup",
      "id": "D77291D6-329F-4236-8F06-C25828CE31FD"
    },
    {
      "class": "text",
      "id": "EA6F2713-0171-478F-90AA-DF8DC17F875A"
    },
    {
      "class": "shapeGroup",
      "id": "32AF1F91-712F-4AFA-B3F1-C650D6750779"
    },
    {
      "class": "text",
      "id": "A3BE0EDA-B519-4CA7-9B2B-3F4DE727A1C9"
    },
    {
      "class": "shapeGroup",
      "id": "6C1C484D-A59A-4AD6-87DD-E3B99D4FE7C0"
    },
    {
      "class": "text",
      "id": "B9F1F500-0782-44AF-A353-C8AEF0CD878A"
    },
    {
      "class": "shapeGroup",
      "id": "13FB2320-28F3-47CC-936E-88AED9F505AE"
    },
    {
      "class": "text",
      "id": "5D958E00-F3B9-43CF-A313-447C7038E3F7"
    },
    {
      "class": "shapeGroup",
      "id": "82FC499A-274F-4FF1-B8DC-9CE6CBABF7E6"
    },
    {
      "class": "text",
      "id": "8773EE36-8A55-48EA-9797-0D167985DB7C"
    }
  ],
  "name": "Medium List",
  "nameIsFixed": true,
  "resizingConstraint": 63,
  "resizingType": 0,
  "rotation": 0,
  "shouldBreakMaskChain": false,
  "style": {
    "_class": "style",
    "do_objectID": "82585DA3-DF42-4618-96D7-93AD860E0523",
    "endMarkerType": 0,
    "miterLimit": 10,
    "startMarkerType": 0,
    "windingRule": 1
  },
  "userInfo": {
    "com.animaapp.stc-sketch-plugin": {
      "kModelPropertiesKey": {
      }
    }
  }
}