{
  "_class": "symbolInstance",
  "booleanOperation": 0,
  "do_objectID": "602FB4F9-6E57-46F5-A1EB-F69DCCF12F66",
  "exportOptions": {
    "_class": "exportOptions",
    "do_objectID": "D4A29EA5-BF36-4016-8216-25CFD48BCA29",
    "exportFormats": [
    ],
    "includedLayerIds": [
    ],
    "layerOptions": 0,
    "shouldTrim": false
  },
  "frame": {
    "_class": "rect",
    "constrainProportions": false,
    "do_objectID": "BFBE3A5D-85DF-4CB2-9BB9-5B372693CBAC",
    "height": 76,
    "width": 364,
    "x": 366,
    "y": 0
  },
  "horizontalSpacing": 0,
  "isFixedToViewport": false,
  "isFlippedHorizontal": false,
  "isFlippedVertical": false,
  "isLocked": false,
  "isVisible": true,
  "layerListExpandedType": 0,
  "name": "Steps/_Resource/TitleStep+Active",
  "nameIsFixed": true,
  "overrideValues": [
  ],
  "resizingConstraint": 63,
  "resizingType": 0,
  "rotation": 0,
  "scale": 1,
  "shouldBreakMaskChain": false,
  "style": {
    "_class": "style",
    "do_objectID": "6258386B-75C9-4154-B972-21B3198B2ABF",
    "endMarkerType": 0,
    "miterLimit": 10,
    "startMarkerType": 0,
    "windingRule": 1
  },
  "symbolID": "C09638B0-C3DB-4961-8FF2-42A0257DA8F5",
  "userInfo": {
    "com.animaapp.stc-sketch-plugin": {
      "kModelPropertiesKey": {
      }
    }
  },
  "verticalSpacing": 0
}