{
  "_class": "group",
  "booleanOperation": -1,
  "do_objectID": "ECDB4DFC-A444-4532-9FBD-A822698EBDDA",
  "exportOptions": {
    "_class": "exportOptions",
    "do_objectID": "163F8DEF-F64B-4B23-A0A3-35DF33142E48",
    "exportFormats": [
    ],
    "includedLayerIds": [
    ],
    "layerOptions": 0,
    "shouldTrim": false
  },
  "frame": {
    "_class": "rect",
    "constrainProportions": false,
    "do_objectID": "FE39900B-0864-43D1-B626-3DD8D9E607D9",
    "height": 168,
    "width": 86,
    "x": 370,
    "y": 303
  },
  "hasClickThrough": false,
  "isFixedToViewport": false,
  "isFlippedHorizontal": false,
  "isFlippedVertical": false,
  "isLocked": false,
  "isVisible": true,
  "layerListExpandedType": 0,
  "layers": [
    {
      "class": "text",
      "id": "80F91FAD-1A38-4748-8F4B-CBE12953D979"
    },
    {
      "class": "symbolInstance",
      "id": "073E5926-588D-4651-B8AB-A5BEF6BE81BC"
    },
    {
      "class": "symbolInstance",
      "id": "C3BF0F76-B27E-4815-8720-419AEC923551"
    },
    {
      "class": "symbolInstance",
      "id": "0D5CAE05-D034-4F80-88AF-B1F3EA1C3F6E"
    }
  ],
  "name": "Danger Button",
  "nameIsFixed": true,
  "resizingConstraint": 63,
  "resizingType": 0,
  "rotation": 0,
  "shouldBreakMaskChain": false,
  "style": {
    "_class": "style",
    "do_objectID": "9F81C10E-6B32-4AE5-A9C8-4F8712DA1E10",
    "endMarkerType": 0,
    "miterLimit": 10,
    "startMarkerType": 0,
    "windingRule": 1
  },
  "userInfo": {
    "com.animaapp.stc-sketch-plugin": {
      "kModelPropertiesKey": {
      }
    }
  }
}