{
  "_class": "shapePath",
  "booleanOperation": -1,
  "do_objectID": "43FD6F6F-9405-4B1E-A9C5-8B9C991FDBA8",
  "edited": true,
  "exportOptions": {
    "_class": "exportOptions",
    "do_objectID": "71523176-02A1-46E0-ABBC-FEC61B8E8DE3",
    "exportFormats": [
    ],
    "includedLayerIds": [
    ],
    "layerOptions": 0,
    "shouldTrim": false
  },
  "frame": {
    "_class": "rect",
    "constrainProportions": false,
    "do_objectID": "CA055E30-5D52-499E-8D40-C60D18FB7D38",
    "height": 20.94375,
    "width": 20.95288370530461,
    "x": 3.552713678800503e-15,
    "y": 0
  },
  "isClosed": true,
  "isFixedToViewport": false,
  "isFlippedHorizontal": false,
  "isFlippedVertical": false,
  "isLocked": false,
  "isVisible": true,
  "layerListExpandedType": 0,
  "name": "Path",
  "nameIsFixed": false,
  "pointRadiusBehaviour": 1,
  "points": [
    {
      "_class": "curvePoint",
      "cornerRadius": 0,
      "curveFrom": "{0.27345360182350675, 0}",
      "curveMode": 4,
      "curveTo": "{0.28296154129388928, 0}",
      "hasCurveFrom": true,
      "hasCurveTo": false,
      "point": "{0.28296154129388928, 0}"
    },
    {
      "_class": "curvePoint",
      "cornerRadius": 0,
      "curveFrom": "{0.25645116888823455, 0.010966875559534463}",
      "curveMode": 4,
      "curveTo": "{0.26383380424170799, 0.0035810205908684005}",
      "hasCurveFrom": false,
      "hasCurveTo": true,
      "point": "{0.25645116888823455, 0.010966875559534463}"
    },
    {
      "_class": "curvePoint",
      "cornerRadius": 0,
      "curveFrom": "{-0.0057442442714898271, 0.27271709937332139}",
      "curveMode": 4,
      "curveTo": "{0.011034472440949874, 0.25593106535362581}",
      "hasCurveFrom": true,
      "hasCurveTo": false,
      "point": "{0.011034472440949874, 0.25593106535362581}"
    },
    {
      "_class": "curvePoint",
      "cornerRadius": 0,
      "curveFrom": "{0.052310115553551549, 0.33672784243509407}",
      "curveMode": 3,
      "curveTo": "{-0.0030596495974994759, 0.30069382273948081}",
      "hasCurveFrom": true,
      "hasCurveTo": true,
      "point": "{0.016851094234595642, 0.31367502238137879}"
    },
    {
      "_class": "curvePoint",
      "cornerRadius": 0,
      "curveFrom": "{0.13597998289291752, 0.34825425246195169}",
      "curveMode": 3,
      "curveTo": "{0.093026468109071878, 0.34825425246195169}",
      "hasCurveFrom": true,
      "hasCurveTo": true,
      "point": "{0.13374282066459223, 0.34825425246195169}"
    },
    {
      "_class": "curvePoint",
      "cornerRadius": 0,
      "curveFrom": "{0.1404543073495681, 0.34814234556848705}",
      "curveMode": 4,
      "curveTo": "{0.13821714512124281, 0.34825425246195169}",
      "hasCurveFrom": false,
      "hasCurveTo": true,
      "point": "{0.1404543073495681, 0.34814234556848705}"
    },
    {
      "_class": "curvePoint",
      "cornerRadius": 0,
      "curveFrom": "{0.28900187931036758, 0.71553267681289168}",
      "curveMode": 4,
      "curveTo": "{0.33061309675721806, 0.58807072515666958}",
      "hasCurveFrom": true,
      "hasCurveTo": false,
      "point": "{0.33061309675721806, 0.58807072515666958}"
    },
    {
      "_class": "curvePoint",
      "cornerRadius": 0,
      "curveFrom": "{0.40846634230293821, 0.97750671441360781}",
      "curveMode": 3,
      "curveTo": "{0.31238022459636688, 0.85944494180841535}",
      "hasCurveFrom": true,
      "hasCurveTo": true,
      "point": "{0.40074813261521597, 0.96810653536257829}"
    },
    {
      "_class": "curvePoint",
      "cornerRadius": 0,
      "curveFrom": "{0.44045776216798993, 0.98231871083258737}",
      "curveMode": 2,
      "curveTo": "{0.41954029533314846, 0.98231871083258737}",
      "hasCurveFrom": true,
      "hasCurveTo": true,
      "point": "{0.43061424836335865, 0.98231871083258737}"
    },
    {
      "_class": "curvePoint",
      "cornerRadius": 0,
      "curveFrom": "{0.45779576943751099, 0.97101611459265891}",
      "curveMode": 4,
      "curveTo": "{0.45018941786120498, 0.97862578334825434}",
      "hasCurveFrom": false,
      "hasCurveTo": true,
      "point": "{0.45779576943751099, 0.97101611459265891}"
    },
    {
      "_class": "curvePoint",
      "cornerRadius": 0,
      "curveFrom": "{0.68822347895501623, 0.73959265890778869}",
      "curveMode": 1,
      "curveTo": "{0.68822347895501623, 0.73959265890778869}",
      "hasCurveFrom": false,
      "hasCurveTo": false,
      "point": "{0.68822347895501623, 0.73959265890778869}"
    },
    {
      "_class": "curvePoint",
      "cornerRadius": 0,
      "curveFrom": "{0.94504970276675992, 0.99653088630259623}",
      "curveMode": 4,
      "curveTo": "{0.93789078363611911, 0.98936884512085943}",
      "hasCurveFrom": true,
      "hasCurveTo": false,
      "point": "{0.93789078363611911, 0.98936884512085943}"
    },
    {
      "_class": "curvePoint",
      "cornerRadius": 0,
      "curveFrom": "{0.97290237250940981, 1}",
      "curveMode": 2,
      "curveTo": "{0.95433392601431, 1}",
      "hasCurveFrom": true,
      "hasCurveTo": true,
      "point": "{0.96361814926185996, 1}"
    },
    {
      "_class": "curvePoint",
      "cornerRadius": 0,
      "curveFrom": "{1.0035514950374664, 0.97515666965085046}",
      "curveMode": 3,
      "curveTo": "{0.98229845386837622, 0.9964189794091316}",
      "hasCurveFrom": true,
      "hasCurveTo": true,
      "point": "{0.98934551488760081, 0.98936884512085943}"
    },
    {
      "_class": "curvePoint",
      "cornerRadius": 0,
      "curveFrom": "{0.98934551488760081, 0.93777976723366152}",
      "curveMode": 4,
      "curveTo": "{1.0035514950374664, 0.9519919427036706}",
      "hasCurveFrom": false,
      "hasCurveTo": true,
      "point": "{0.98934551488760081, 0.93777976723366152}"
    },
    {
      "_class": "curvePoint",
      "cornerRadius": 0,
      "curveFrom": "{0.7395663520950817, 0.68800358102059078}",
      "curveMode": 1,
      "curveTo": "{0.7395663520950817, 0.68800358102059078}",
      "hasCurveFrom": false,
      "hasCurveTo": false,
      "point": "{0.7395663520950817, 0.68800358102059078}"
    },
    {
      "_class": "curvePoint",
      "cornerRadius": 0,
      "curveFrom": "{0.98610162965652903, 0.44046553267681293}",
      "curveMode": 4,
      "curveTo": "{0.96999406161258694, 0.45658012533572068}",
      "hasCurveFrom": true,
      "hasCurveTo": false,
      "point": "{0.96999406161258694, 0.45658012533572068}"
    },
    {
      "_class": "curvePoint",
      "cornerRadius": 0,
      "curveFrom": "{0.89325939718102954, 0.3400850492390331}",
      "curveMode": 3,
      "curveTo": "{0.98453561609670137, 0.41394359892569377}",
      "hasCurveFrom": true,
      "hasCurveTo": true,
      "point": "{0.96686203449293162, 0.39950760966875559}"
    },
    {
      "_class": "curvePoint",
      "cornerRadius": 0,
      "curveFrom": "{0.67144476224257654, 0.31031781557743954}",
      "curveMode": 3,
      "curveTo": "{0.80354919182518514, 0.31031781557743954}",
      "hasCurveFrom": true,
      "hasCurveTo": true,
      "point": "{0.71395084458075708, 0.31031781557743954}"
    },
    {
      "_class": "curvePoint",
      "cornerRadius": 0,
      "curveFrom": "{0.5882223273488757, 0.33034914950760957}",
      "curveMode": 4,
      "curveTo": "{0.62905053801581223, 0.31703222918531776}",
      "hasCurveFrom": false,
      "hasCurveTo": true,
      "point": "{0.5882223273488757, 0.33034914950760957}"
    },
    {
      "_class": "curvePoint",
      "cornerRadius": 0,
      "curveFrom": "{0.34974083380939941, 0.097247090420769858}",
      "curveMode": 4,
      "curveTo": "{0.34839853647240421, 0.14010743061772601}",
      "hasCurveFrom": true,
      "hasCurveTo": false,
      "point": "{0.34839853647240421, 0.14010743061772601}"
    },
    {
      "_class": "curvePoint",
      "cornerRadius": 0,
      "curveFrom": "{0.30689917713696996, 0.0058191584601611493}",
      "curveMode": 3,
      "curveTo": "{0.33833130644494042, 0.054162936436884468}",
      "hasCurveFrom": true,
      "hasCurveTo": true,
      "point": "{0.31416995437902723, 0.016897940913160211}"
    },
    {
      "_class": "curvePoint",
      "cornerRadius": 0,
      "curveFrom": "{0.28296154129388928, 0}",
      "curveMode": 4,
      "curveTo": "{0.29504221732684588, 0}",
      "hasCurveFrom": false,
      "hasCurveTo": true,
      "point": "{0.28296154129388928, 0}"
    }
  ],
  "resizingConstraint": 63,
  "resizingType": 0,
  "rotation": 0,
  "shouldBreakMaskChain": false
}