{
  "_class": "symbolInstance",
  "booleanOperation": 0,
  "do_objectID": "EECCE5B7-A654-47D6-8BDA-01BEAC3C9569",
  "exportOptions": {
    "_class": "exportOptions",
    "do_objectID": "E97ECEC6-E625-4D9B-8E1E-0CFD5AC722FA",
    "exportFormats": [
    ],
    "includedLayerIds": [
    ],
    "layerOptions": 0,
    "shouldTrim": false
  },
  "frame": {
    "_class": "rect",
    "constrainProportions": false,
    "do_objectID": "21DCF42E-D060-49BE-B017-EF1DECDC4E83",
    "height": 32,
    "width": 78,
    "x": 77,
    "y": 0
  },
  "horizontalSpacing": 0,
  "isFixedToViewport": false,
  "isFlippedHorizontal": false,
  "isFlippedVertical": false,
  "isLocked": false,
  "isVisible": true,
  "layerListExpandedType": 0,
  "name": "RadioButton/_Resource/Default/Option+Normal",
  "nameIsFixed": false,
  "overrideValues": [
  ],
  "resizingConstraint": 63,
  "resizingType": 0,
  "rotation": 0,
  "scale": 1,
  "shouldBreakMaskChain": false,
  "style": {
    "_class": "style",
    "do_objectID": "811BB032-4EF4-414E-A01E-9818627CAEB2",
    "endMarkerType": 0,
    "miterLimit": 10,
    "startMarkerType": 0,
    "windingRule": 1
  },
  "symbolID": "42B778A7-180A-4E78-9556-39AFC73C5CE2",
  "userInfo": {
    "com.animaapp.stc-sketch-plugin": {
      "kModelPropertiesKey": {
      }
    }
  },
  "verticalSpacing": 0
}