{
  "_class": "shapePath",
  "booleanOperation": -1,
  "do_objectID": "CB4D931A-7017-42C8-9D5C-710C2CE20D9D",
  "edited": true,
  "exportOptions": {
    "_class": "exportOptions",
    "do_objectID": "2991B1C8-9D2E-4ADB-BBAB-F637F7008500",
    "exportFormats": [
    ],
    "includedLayerIds": [
    ],
    "layerOptions": 0,
    "shouldTrim": false
  },
  "frame": {
    "_class": "rect",
    "constrainProportions": false,
    "do_objectID": "6EE9F380-5395-4260-B880-0B947AA09756",
    "height": 5.847070312500001,
    "width": 16.47363281250001,
    "x": 0,
    "y": 10.40332031250001
  },
  "isClosed": true,
  "isFixedToViewport": false,
  "isFlippedHorizontal": false,
  "isFlippedVertical": false,
  "isLocked": false,
  "isVisible": true,
  "layerListExpandedType": 0,
  "name": "Path",
  "nameIsFixed": false,
  "pointRadiusBehaviour": 1,
  "points": [
    {
      "_class": "curvePoint",
      "cornerRadius": 0,
      "curveFrom": "{0.95308554152587555, 0.00040084176771228663}",
      "curveMode": 4,
      "curveTo": "{0.95237417748532782, 0}",
      "hasCurveFrom": true,
      "hasCurveTo": true,
      "point": "{0.95265872310154698, 0.00040084176771228663}"
    },
    {
      "_class": "curvePoint",
      "cornerRadius": 0,
      "curveFrom": "{0.95450826960697099, 0.00080168353542457325}",
      "curveMode": 4,
      "curveTo": "{0.95351235995020422, 0.00040084176771228663}",
      "hasCurveFrom": true,
      "hasCurveTo": true,
      "point": "{0.9539391783745329, 0.00080168353542457325}"
    },
    {
      "_class": "curvePoint",
      "cornerRadius": 0,
      "curveFrom": "{0.95578872487995714, 0.0012025253031368599}",
      "curveMode": 2,
      "curveTo": "{0.95493508803129978, 0.0012025253031368599}",
      "hasCurveFrom": true,
      "hasCurveTo": true,
      "point": "{0.95550417926373798, 0.0012025253031368599}"
    },
    {
      "_class": "curvePoint",
      "cornerRadius": 0,
      "curveFrom": "{0.95706918015294307, 0.0020042088385614329}",
      "curveMode": 4,
      "curveTo": "{0.95621554330428571, 0.0016033670708491465}",
      "hasCurveFrom": true,
      "hasCurveTo": true,
      "point": "{0.95650008892050487, 0.0016033670708491465}"
    },
    {
      "_class": "curvePoint",
      "cornerRadius": 0,
      "curveFrom": "{0.9583496354259291, 0.0024050506062737198}",
      "curveMode": 4,
      "curveTo": "{0.95763827138538116, 0.0020042088385614329}",
      "hasCurveFrom": true,
      "hasCurveTo": true,
      "point": "{0.95806508980970995, 0.0024050506062737198}"
    },
    {
      "_class": "curvePoint",
      "cornerRadius": 0,
      "curveFrom": "{0.95948781789080539, 0.003206734141698293}",
      "curveMode": 4,
      "curveTo": "{0.95863418104214815, 0.0028058923739860062}",
      "hasCurveFrom": true,
      "hasCurveTo": true,
      "point": "{0.9589187266583673, 0.0028058923739860062}"
    },
    {
      "_class": "curvePoint",
      "cornerRadius": 0,
      "curveFrom": "{0.96076827316379154, 0.0040084176771224105}",
      "curveMode": 4,
      "curveTo": "{0.9600569091232436, 0.0036075759094105794}",
      "hasCurveFrom": true,
      "hasCurveTo": true,
      "point": "{0.96048372754757239, 0.0040084176771224105}"
    },
    {
      "_class": "curvePoint",
      "cornerRadius": 0,
      "curveFrom": "{0.96190645562866783, 0.0048101012125469841}",
      "curveMode": 4,
      "curveTo": "{0.96105281878001048, 0.0044092594448346973}",
      "hasCurveFrom": true,
      "hasCurveTo": true,
      "point": "{0.96133736439622963, 0.0044092594448346973}"
    },
    {
      "_class": "curvePoint",
      "cornerRadius": 0,
      "curveFrom": "{0.96318691090165398, 0.0060126265156833876}",
      "curveMode": 4,
      "curveTo": "{0.96233327405299662, 0.0052109429802592701}",
      "hasCurveFrom": true,
      "hasCurveTo": true,
      "point": "{0.96290236528543471, 0.0056117847479711016}"
    },
    {
      "_class": "curvePoint",
      "cornerRadius": 0,
      "curveFrom": "{0.96418282055842064, 0.0068143100511079613}",
      "curveMode": 4,
      "curveTo": "{0.96347145651787292, 0.0060126265156833876}",
      "hasCurveFrom": true,
      "hasCurveTo": true,
      "point": "{0.96375600213409207, 0.0064134682833956744}"
    },
    {
      "_class": "curvePoint",
      "cornerRadius": 0,
      "curveFrom": "{0.96546327583140679, 0.0080168353542443647}",
      "curveMode": 4,
      "curveTo": "{0.96475191179085906, 0.0072151518188202481}",
      "hasCurveFrom": true,
      "hasCurveTo": true,
      "point": "{0.96517873021518763, 0.0076159935865320787}"
    },
    {
      "_class": "curvePoint",
      "cornerRadius": 0,
      "curveFrom": "{0.96660145829628308, 0.0088185188896689384}",
      "curveMode": 4,
      "curveTo": "{0.96589009425573535, 0.0084176771219566515}",
      "hasCurveFrom": true,
      "hasCurveTo": true,
      "point": "{0.96617463987195451, 0.0084176771219566515}"
    },
    {
      "_class": "curvePoint",
      "cornerRadius": 0,
      "curveFrom": "{0.967881913569269, 0.010021044192805343}",
      "curveMode": 2,
      "curveTo": "{0.96702827672061187, 0.0092193606573812252}",
      "hasCurveFrom": true,
      "hasCurveTo": true,
      "point": "{0.96745509514494044, 0.0096202024250930558}"
    },
    {
      "_class": "curvePoint",
      "cornerRadius": 0,
      "curveFrom": "{0.96902009603414541, 0.011223569495941747}",
      "curveMode": 2,
      "curveTo": "{0.96816645918548816, 0.010421885960517629}",
      "hasCurveFrom": true,
      "hasCurveTo": true,
      "point": "{0.96859327760981673, 0.01082272772822946}"
    },
    {
      "_class": "curvePoint",
      "cornerRadius": 0,
      "curveFrom": "{0.9701582784990217, 0.012426094799078151}",
      "curveMode": 2,
      "curveTo": "{0.96930464165036456, 0.011624411263654034}",
      "hasCurveFrom": true,
      "hasCurveTo": true,
      "point": "{0.96973146007469313, 0.012025253031365864}"
    },
    {
      "_class": "curvePoint",
      "cornerRadius": 0,
      "curveFrom": "{0.97129646096389821, 0.014029461869926842}",
      "curveMode": 4,
      "curveTo": "{0.97058509692335049, 0.013227778334502269}",
      "hasCurveFrom": true,
      "hasCurveTo": true,
      "point": "{0.97101191534767906, 0.013628620102214556}"
    },
    {
      "_class": "curvePoint",
      "cornerRadius": 0,
      "curveFrom": "{0.9724346434287745, 0.015632828940775532}",
      "curveMode": 4,
      "curveTo": "{0.97158100658011715, 0.014430303637639129}",
      "hasCurveFrom": true,
      "hasCurveTo": true,
      "point": "{0.97200782500444594, 0.01483114540535096}"
    },
    {
      "_class": "curvePoint",
      "cornerRadius": 0,
      "curveFrom": "{0.97357282589365102, 0.017236196011624225}",
      "curveMode": 4,
      "curveTo": "{0.97286146185310329, 0.016033670708487362}",
      "hasCurveFrom": true,
      "hasCurveTo": true,
      "point": "{0.97328828027743186, 0.016835354243911936}"
    },
    {
      "_class": "curvePoint",
      "cornerRadius": 0,
      "curveFrom": "{0.97456873555041779, 0.018839563082472914}",
      "curveMode": 4,
      "curveTo": "{0.97385737150987006, 0.01763703777933651}",
      "hasCurveFrom": true,
      "hasCurveTo": true,
      "point": "{0.97414191712608922, 0.01803787954704834}"
    },
    {
      "_class": "curvePoint",
      "cornerRadius": 0,
      "curveFrom": "{0.97584919082340382, 0.020843771921033892}",
      "curveMode": 4,
      "curveTo": "{0.9751378267828561, 0.019641246617897033}",
      "hasCurveFrom": true,
      "hasCurveTo": true,
      "point": "{0.97556464520718467, 0.020442930153321603}"
    },
    {
      "_class": "curvePoint",
      "cornerRadius": 0,
      "curveFrom": "{0.97670282767206107, 0.022447138991882581}",
      "curveMode": 4,
      "curveTo": "{0.97599146363151323, 0.021244613688746177}",
      "hasCurveFrom": true,
      "hasCurveTo": true,
      "point": "{0.97627600924773239, 0.021645455456458008}"
    },
    {
      "_class": "curvePoint",
      "cornerRadius": 0,
      "curveFrom": "{0.97798328294504711, 0.024451347830443559}",
      "curveMode": 4,
      "curveTo": "{0.97727191890449938, 0.023248822527306701}",
      "hasCurveFrom": true,
      "hasCurveTo": true,
      "point": "{0.97769873732882795, 0.024050506062731274}"
    },
    {
      "_class": "curvePoint",
      "cornerRadius": 0,
      "curveFrom": "{0.97883691979370424, 0.026054714901292252}",
      "curveMode": 4,
      "curveTo": "{0.97812555575315652, 0.024852189598155848}",
      "hasCurveFrom": true,
      "hasCurveTo": true,
      "point": "{0.97841010136937567, 0.025253031365867679}"
    },
    {
      "_class": "curvePoint",
      "cornerRadius": 0,
      "curveFrom": "{0.97997510225858075, 0.028459765507565515}",
      "curveMode": 4,
      "curveTo": "{0.97926373821803303, 0.026856398436716368}",
      "hasCurveFrom": true,
      "hasCurveTo": true,
      "point": "{0.9796905566423616, 0.028058923739853227}"
    },
    {
      "_class": "curvePoint",
      "cornerRadius": 0,
      "curveFrom": "{0.98082873910723789, 0.030463974346126493}",
      "curveMode": 4,
      "curveTo": "{0.9802596478747998, 0.029261449042989631}",
      "hasCurveFrom": true,
      "hasCurveTo": true,
      "point": "{0.98040192068290932, 0.02966229081070192}"
    },
    {
      "_class": "curvePoint",
      "cornerRadius": 0,
      "curveFrom": "{0.98182464876400488, 0.033269866720112042}",
      "curveMode": 4,
      "curveTo": "{0.98125555753156668, 0.031265657881550613}",
      "hasCurveFrom": true,
      "hasCurveTo": true,
      "point": "{0.98154010314778573, 0.032468183184687471}"
    },
    {
      "_class": "curvePoint",
      "cornerRadius": 0,
      "curveFrom": "{0.98282055842077176, 0.035674917326385308}",
      "curveMode": 2,
      "curveTo": "{0.98225146718833345, 0.034071550255536161}",
      "hasCurveFrom": true,
      "hasCurveTo": true,
      "point": "{0.98253601280455261, 0.034873233790960731}"
    },
    {
      "_class": "curvePoint",
      "cornerRadius": 0,
      "curveFrom": "{0.98467010492619589, 0.040084176771219095}",
      "curveMode": 4,
      "curveTo": "{0.98310510403699081, 0.036476600861809427}",
      "hasCurveFrom": true,
      "hasCurveTo": true,
      "point": "{0.98338964965320996, 0.036877442629521709}"
    },
    {
      "_class": "curvePoint",
      "cornerRadius": 0,
      "curveFrom": "{0.98723101547216785, 0.047700170357751169}",
      "curveMode": 4,
      "curveTo": "{0.9858082873910724, 0.043290910912916931}",
      "hasCurveFrom": true,
      "hasCurveTo": true,
      "point": "{0.98694646985594869, 0.046898486822326599}"
    },
    {
      "_class": "curvePoint",
      "cornerRadius": 0,
      "curveFrom": "{0.98794237951271557, 0.050105220964024436}",
      "curveMode": 4,
      "curveTo": "{0.9875155610883869, 0.048501853893175288}",
      "hasCurveFrom": true,
      "hasCurveTo": true,
      "point": "{0.98765783389649642, 0.049303537428599865}"
    },
    {
      "_class": "curvePoint",
      "cornerRadius": 0,
      "curveFrom": "{0.98879601636137293, 0.053311955105721814}",
      "curveMode": 4,
      "curveTo": "{0.98822692512893462, 0.051307746267160836}",
      "hasCurveFrom": true,
      "hasCurveTo": true,
      "point": "{0.98851147074515378, 0.052109429802585414}"
    },
    {
      "_class": "curvePoint",
      "cornerRadius": 0,
      "curveFrom": "{0.98964965321003029, 0.05611784747970737}",
      "curveMode": 4,
      "curveTo": "{0.98908056197759198, 0.05451448040885868}",
      "hasCurveFrom": true,
      "hasCurveTo": true,
      "point": "{0.98950738040192066, 0.055316163944282792}"
    },
    {
      "_class": "curvePoint",
      "cornerRadius": 0,
      "curveFrom": "{0.99036101725057801, 0.058522898085980178}",
      "curveMode": 4,
      "curveTo": "{0.98993419882624922, 0.056919531015131482}",
      "hasCurveFrom": true,
      "hasCurveTo": true,
      "point": "{0.99007647163435886, 0.05732037278284377}"
    },
    {
      "_class": "curvePoint",
      "cornerRadius": 0,
      "curveFrom": "{0.99121465409923537, 0.061729632227678015}",
      "curveMode": 4,
      "curveTo": "{0.99064556286679706, 0.059725423389117037}",
      "hasCurveFrom": true,
      "hasCurveTo": true,
      "point": "{0.99107238129112574, 0.060927948692253438}"
    },
    {
      "_class": "curvePoint",
      "cornerRadius": 0,
      "curveFrom": "{0.99178374533167357, 0.064134682833950823}",
      "curveMode": 4,
      "curveTo": "{0.99135692690734489, 0.062130473995389845}",
      "hasCurveFrom": true,
      "hasCurveTo": true,
      "point": "{0.9914991997154543, 0.062932157530814423}"
    },
    {
      "_class": "curvePoint",
      "cornerRadius": 0,
      "curveFrom": "{0.9924951093722213, 0.067742258743360942}",
      "curveMode": 4,
      "curveTo": "{0.99206829094789251, 0.065738049904799964}",
      "hasCurveFrom": true,
      "hasCurveTo": true,
      "point": "{0.99235283656411166, 0.066940575207936379}"
    },
    {
      "_class": "curvePoint",
      "cornerRadius": 0,
      "curveFrom": "{0.99306420060465939, 0.070147309349633757}",
      "curveMode": 4,
      "curveTo": "{0.99263738218033082, 0.068143100511072779}",
      "hasCurveFrom": true,
      "hasCurveTo": true,
      "point": "{0.99277965498844023, 0.068944784046497343}"
    },
    {
      "_class": "curvePoint",
      "cornerRadius": 0,
      "curveFrom": "{0.99377556464520722, 0.073754885259043876}",
      "curveMode": 4,
      "curveTo": "{0.99334874622087843, 0.071750676420482898}",
      "hasCurveFrom": true,
      "hasCurveTo": true,
      "point": "{0.99363329183709759, 0.072953201723619299}"
    },
    {
      "_class": "curvePoint",
      "cornerRadius": 0,
      "curveFrom": "{0.99434465587764531, 0.076560777633028973}",
      "curveMode": 4,
      "curveTo": "{0.99391783745331674, 0.074556568794467995}",
      "hasCurveFrom": true,
      "hasCurveTo": true,
      "point": "{0.99406011026142616, 0.075358252329892572}"
    },
    {
      "_class": "curvePoint",
      "cornerRadius": 0,
      "curveFrom": "{0.99491374711008351, 0.07976751177472681}",
      "curveMode": 4,
      "curveTo": "{0.99448692868575472, 0.077763302936165832}",
      "hasCurveFrom": true,
      "hasCurveTo": true,
      "point": "{0.99477147430197399, 0.078965828239302233}"
    },
    {
      "_class": "curvePoint",
      "cornerRadius": 0,
      "curveFrom": "{0.99534056553441208, 0.082573404148711907}",
      "curveMode": 4,
      "curveTo": "{0.99505601991819315, 0.080569195310150929}",
      "hasCurveFrom": true,
      "hasCurveTo": true,
      "point": "{0.99519829272630256, 0.081370878845575506}"
    },
    {
      "_class": "curvePoint",
      "cornerRadius": 0,
      "curveFrom": "{0.99590965676685028, 0.086180980058121567}",
      "curveMode": 2,
      "curveTo": "{0.99562511115063113, 0.083775929451848766}",
      "hasCurveFrom": true,
      "hasCurveTo": true,
      "point": "{0.99576738395874065, 0.084978454754985167}"
    },
    {
      "_class": "curvePoint",
      "cornerRadius": 0,
      "curveFrom": "{0.99633647519117885, 0.08938771419981896}",
      "curveMode": 2,
      "curveTo": "{0.9960519295749598, 0.086982663593546145}",
      "hasCurveFrom": true,
      "hasCurveTo": true,
      "point": "{0.99619420238306933, 0.088185188896682545}"
    },
    {
      "_class": "curvePoint",
      "cornerRadius": 0,
      "curveFrom": "{0.99676329361550742, 0.092594448341516339}",
      "curveMode": 2,
      "curveTo": "{0.99647874799928848, 0.090189397735243523}",
      "hasCurveFrom": true,
      "hasCurveTo": true,
      "point": "{0.99662102080739789, 0.091391923038379938}"
    },
    {
      "_class": "curvePoint",
      "cornerRadius": 0,
      "curveFrom": "{0.99719011203983599, 0.095801182483214176}",
      "curveMode": 4,
      "curveTo": "{0.99690556642361705, 0.093796973644653198}",
      "hasCurveFrom": true,
      "hasCurveTo": true,
      "point": "{0.99704783923172646, 0.094999498947789598}"
    },
    {
      "_class": "curvePoint",
      "cornerRadius": 0,
      "curveFrom": "{0.99747465765605514, 0.099007916624911554}",
      "curveMode": 4,
      "curveTo": "{0.99733238484794562, 0.097003707786350576}",
      "hasCurveFrom": true,
      "hasCurveTo": true,
      "point": "{0.99733238484794562, 0.097805391321775154}"
    },
    {
      "_class": "curvePoint",
      "cornerRadius": 0,
      "curveFrom": "{0.99790147608038382, 0.10261549253432167}",
      "curveMode": 4,
      "curveTo": "{0.99761693046416478, 0.10061128369576069}",
      "hasCurveFrom": true,
      "hasCurveTo": true,
      "point": "{0.99775920327227419, 0.10181380899889711}"
    },
    {
      "_class": "curvePoint",
      "cornerRadius": 0,
      "curveFrom": "{0.99818602169660298, 0.10582222667601907}",
      "curveMode": 4,
      "curveTo": "{0.99790147608038382, 0.10341717606974579}",
      "hasCurveFrom": true,
      "hasCurveTo": true,
      "point": "{0.99804374888849334, 0.10421885960517037}"
    },
    {
      "_class": "curvePoint",
      "cornerRadius": 0,
      "curveFrom": "{0.99847056731282191, 0.10942980258542918}",
      "curveMode": 4,
      "curveTo": "{0.9983282945047125, 0.10702475197915592}",
      "hasCurveFrom": true,
      "hasCurveTo": true,
      "point": "{0.99847056731282191, 0.10862811905000461}"
    },
    {
      "_class": "curvePoint",
      "cornerRadius": 0,
      "curveFrom": "{0.99875511292904107, 0.11263653672712656}",
      "curveMode": 4,
      "curveTo": "{0.99861284012093154, 0.1102314861208533}",
      "hasCurveFrom": true,
      "hasCurveTo": true,
      "point": "{0.99861284012093154, 0.11103316965627788}"
    },
    {
      "_class": "curvePoint",
      "cornerRadius": 0,
      "curveFrom": "{0.9988973857371507, 0.1162441126365367}",
      "curveMode": 2,
      "curveTo": "{0.9988973857371507, 0.11423990379797526}",
      "hasCurveFrom": true,
      "hasCurveTo": true,
      "point": "{0.9988973857371507, 0.11544242910111212}"
    },
    {
      "_class": "curvePoint",
      "cornerRadius": 0,
      "curveFrom": "{0.99918193135336986, 0.11945084677823407}",
      "curveMode": 4,
      "curveTo": "{0.99903965854526033, 0.11704579617196081}",
      "hasCurveFrom": true,
      "hasCurveTo": true,
      "point": "{0.99903965854526033, 0.11784747970738538}"
    },
    {
      "_class": "curvePoint",
      "cornerRadius": 0,
      "curveFrom": "{0.99932420416147949, 0.12305842268764419}",
      "curveMode": 4,
      "curveTo": "{0.99918193135336986, 0.12105421384908276}",
      "hasCurveFrom": true,
      "hasCurveTo": true,
      "point": "{0.99932420416147949, 0.12225673915221963}"
    },
    {
      "_class": "curvePoint",
      "cornerRadius": 0,
      "curveFrom": "{0.99946647696958901, 0.12666599859705385}",
      "curveMode": 2,
      "curveTo": "{0.99946647696958901, 0.12426094799078059}",
      "hasCurveFrom": true,
      "hasCurveTo": true,
      "point": "{0.99946647696958901, 0.12506263152620517}"
    },
    {
      "_class": "curvePoint",
      "cornerRadius": 0,
      "curveFrom": "{0.99960874977769865, 0.13067441627417581}",
      "curveMode": 2,
      "curveTo": "{0.99960874977769865, 0.12786852390019071}",
      "hasCurveFrom": true,
      "hasCurveTo": true,
      "point": "{0.99960874977769865, 0.12947189097103942}"
    },
    {
      "_class": "curvePoint",
      "cornerRadius": 0,
      "curveFrom": "{0.99975102258580817, 0.1342819921835855}",
      "curveMode": 4,
      "curveTo": "{0.99960874977769865, 0.13187694157731267}",
      "hasCurveFrom": true,
      "hasCurveTo": true,
      "point": "{0.99975102258580817, 0.13307946688044908}"
    },
    {
      "_class": "curvePoint",
      "cornerRadius": 0,
      "curveFrom": "{1.0000355682020274, 0.14109630223469299}",
      "curveMode": 4,
      "curveTo": "{0.99975102258580817, 0.13548451748672236}",
      "hasCurveFrom": true,
      "hasCurveTo": true,
      "point": "{0.9998932953939178, 0.13628620102214647}"
    },
    {
      "_class": "curvePoint",
      "cornerRadius": 0,
      "curveFrom": "{0.9998932953939178, 0.151919029962922}",
      "curveMode": 4,
      "curveTo": "{1.0000355682020274, 0.14590640344723907}",
      "hasCurveFrom": true,
      "hasCurveTo": true,
      "point": "{0.9998932953939178, 0.15071650465978559}"
    },
    {
      "_class": "curvePoint",
      "cornerRadius": 0,
      "curveFrom": "{0.99975102258580817, 0.15512576410461937}",
      "curveMode": 4,
      "curveTo": "{0.9998932953939178, 0.15312155526605886}",
      "hasCurveFrom": true,
      "hasCurveTo": true,
      "point": "{0.99975102258580817, 0.15392323880148298}"
    },
    {
      "_class": "curvePoint",
      "cornerRadius": 0,
      "curveFrom": "{0.99960874977769865, 0.15913418178174132}",
      "curveMode": 4,
      "curveTo": "{0.99975102258580817, 0.15632828940775623}",
      "hasCurveFrom": true,
      "hasCurveTo": true,
      "point": "{0.99960874977769865, 0.15753081471089264}"
    },
    {
      "_class": "curvePoint",
      "cornerRadius": 0,
      "curveFrom": "{0.99946647696958901, 0.16274175769115146}",
      "curveMode": 2,
      "curveTo": "{0.99946647696958901, 0.16033670708487818}",
      "hasCurveFrom": true,
      "hasCurveTo": true,
      "point": "{0.99946647696958901, 0.16194007415572689}"
    },
    {
      "_class": "curvePoint",
      "cornerRadius": 0,
      "curveFrom": "{0.99918193135336986, 0.16634933360056112}",
      "curveMode": 4,
      "curveTo": "{0.99932420416147949, 0.16394428299428787}",
      "hasCurveFrom": true,
      "hasCurveTo": true,
      "point": "{0.99932420416147949, 0.16474596652971243}"
    },
    {
      "_class": "curvePoint",
      "cornerRadius": 0,
      "curveFrom": "{0.99903965854526033, 0.16995690950997125}",
      "curveMode": 4,
      "curveTo": "{0.99918193135336986, 0.16795270067140983}",
      "hasCurveFrom": true,
      "hasCurveTo": true,
      "point": "{0.99903965854526033, 0.16915522597454669}"
    },
    {
      "_class": "curvePoint",
      "cornerRadius": 0,
      "curveFrom": "{0.99875511292904107, 0.17316364365166864}",
      "curveMode": 4,
      "curveTo": "{0.9988973857371507, 0.17075859304539537}",
      "hasCurveFrom": true,
      "hasCurveTo": true,
      "point": "{0.9988973857371507, 0.17156027658081993}"
    },
    {
      "_class": "curvePoint",
      "cornerRadius": 0,
      "curveFrom": "{0.99861284012093154, 0.17677121956107875}",
      "curveMode": 2,
      "curveTo": "{0.99861284012093154, 0.17476701072251732}",
      "hasCurveFrom": true,
      "hasCurveTo": true,
      "point": "{0.99861284012093154, 0.17596953602565418}"
    },
    {
      "_class": "curvePoint",
      "cornerRadius": 0,
      "curveFrom": "{0.99832829450471239, 0.17997795370277614}",
      "curveMode": 4,
      "curveTo": "{0.99847056731282191, 0.17757290309650287}",
      "hasCurveFrom": true,
      "hasCurveTo": true,
      "point": "{0.99847056731282191, 0.17837458663192746}"
    },
    {
      "_class": "curvePoint",
      "cornerRadius": 0,
      "curveFrom": "{0.99790147608038382, 0.18358552961218627}",
      "curveMode": 4,
      "curveTo": "{0.99818602169660275, 0.181180479005913}",
      "hasCurveFrom": true,
      "hasCurveTo": true,
      "point": "{0.99804374888849334, 0.18278384607676168}"
    },
    {
      "_class": "curvePoint",
      "cornerRadius": 0,
      "curveFrom": "{0.99761693046416466, 0.18639142198617137}",
      "curveMode": 4,
      "curveTo": "{0.99790147608038382, 0.18438721314761039}",
      "hasCurveFrom": true,
      "hasCurveTo": true,
      "point": "{0.99775920327227419, 0.18518889668303495}"
    },
    {
      "_class": "curvePoint",
      "cornerRadius": 0,
      "curveFrom": "{0.99719011203983599, 0.18999899789558147}",
      "curveMode": 4,
      "curveTo": "{0.99747465765605503, 0.18799478905702049}",
      "hasCurveFrom": true,
      "hasCurveTo": true,
      "point": "{0.99733238484794562, 0.18919731436015691}"
    },
    {
      "_class": "curvePoint",
      "cornerRadius": 0,
      "curveFrom": "{0.99690556642361683, 0.19320573203727887}",
      "curveMode": 4,
      "curveTo": "{0.99704783923172646, 0.19120152319871789}",
      "hasCurveFrom": true,
      "hasCurveTo": true,
      "point": "{0.99704783923172646, 0.19200320673414245}"
    },
    {
      "_class": "curvePoint",
      "cornerRadius": 0,
      "curveFrom": "{0.99647874799928826, 0.19681330794668853}",
      "curveMode": 2,
      "curveTo": "{0.99676329361550731, 0.19440825734041572}",
      "hasCurveFrom": true,
      "hasCurveTo": true,
      "point": "{0.99662102080739789, 0.19561078264355211}"
    },
    {
      "_class": "curvePoint",
      "cornerRadius": 0,
      "curveFrom": "{0.99605192957495969, 0.20002004208838592}",
      "curveMode": 2,
      "curveTo": "{0.99633647519117874, 0.19761499148211309}",
      "hasCurveFrom": true,
      "hasCurveTo": true,
      "point": "{0.99619420238306933, 0.1988175167852495}"
    },
    {
      "_class": "curvePoint",
      "cornerRadius": 0,
      "curveFrom": "{0.99562511115063113, 0.20322677623008328}",
      "curveMode": 2,
      "curveTo": "{0.99590965676685006, 0.20082172562381048}",
      "hasCurveFrom": true,
      "hasCurveTo": true,
      "point": "{0.99576738395874065, 0.2020242509269469}"
    },
    {
      "_class": "curvePoint",
      "cornerRadius": 0,
      "curveFrom": "{0.99505601991819292, 0.20643351037178112}",
      "curveMode": 4,
      "curveTo": "{0.99534056553441208, 0.20442930153322014}",
      "hasCurveFrom": true,
      "hasCurveTo": true,
      "point": "{0.99519829272630256, 0.20563182683635656}"
    },
    {
      "_class": "curvePoint",
      "cornerRadius": 0,
      "curveFrom": "{0.99448692868575472, 0.20923940274576622}",
      "curveMode": 4,
      "curveTo": "{0.9949137471100834, 0.20723519390720524}",
      "hasCurveFrom": true,
      "hasCurveTo": true,
      "point": "{0.99477147430197399, 0.20803687744262983}"
    },
    {
      "_class": "curvePoint",
      "cornerRadius": 0,
      "curveFrom": "{0.99391783745331663, 0.21244613688746405}",
      "curveMode": 4,
      "curveTo": "{0.99434465587764531, 0.21044192804890308}",
      "hasCurveFrom": true,
      "hasCurveTo": true,
      "point": "{0.99406011026142616, 0.21164445335203949}"
    },
    {
      "_class": "curvePoint",
      "cornerRadius": 0,
      "curveFrom": "{0.99334874622087843, 0.21525202926144915}",
      "curveMode": 4,
      "curveTo": "{0.993775564645207, 0.21324782042288817}",
      "hasCurveFrom": true,
      "hasCurveTo": true,
      "point": "{0.99363329183709759, 0.21404950395831276}"
    },
    {
      "_class": "curvePoint",
      "cornerRadius": 0,
      "curveFrom": "{0.99263738218033071, 0.21885960517085928}",
      "curveMode": 4,
      "curveTo": "{0.99306420060465939, 0.21685539633229831}",
      "hasCurveFrom": true,
      "hasCurveTo": true,
      "point": "{0.99277965498844023, 0.21805792163543472}"
    },
    {
      "_class": "curvePoint",
      "cornerRadius": 0,
      "curveFrom": "{0.99206829094789251, 0.22126465577713209}",
      "curveMode": 4,
      "curveTo": "{0.99249510937222107, 0.21926044693857111}",
      "hasCurveFrom": true,
      "hasCurveTo": true,
      "point": "{0.99235283656411166, 0.2200621304739957}"
    },
    {
      "_class": "curvePoint",
      "cornerRadius": 0,
      "curveFrom": "{0.99135692690734478, 0.22487223168654222}",
      "curveMode": 4,
      "curveTo": "{0.99178374533167357, 0.22286802284798124}",
      "hasCurveFrom": true,
      "hasCurveTo": true,
      "point": "{0.9914991997154543, 0.22407054815111763}"
    },
    {
      "_class": "curvePoint",
      "cornerRadius": 0,
      "curveFrom": "{0.99078783567490658, 0.22727728229281502}",
      "curveMode": 4,
      "curveTo": "{0.99121465409923515, 0.22527307345425404}",
      "hasCurveFrom": true,
      "hasCurveTo": true,
      "point": "{0.99107238129112574, 0.2260747569896786}"
    },
    {
      "_class": "curvePoint",
      "cornerRadius": 0,
      "curveFrom": "{0.98993419882624922, 0.23048401643451286}",
      "curveMode": 4,
      "curveTo": "{0.99050329005868765, 0.22847980759595188}",
      "hasCurveFrom": true,
      "hasCurveTo": true,
      "point": "{0.99007647163435886, 0.22968233289908829}"
    },
    {
      "_class": "curvePoint",
      "cornerRadius": 0,
      "curveFrom": "{0.9892228347857015, 0.23288906704078566}",
      "curveMode": 4,
      "curveTo": "{0.98964965321003029, 0.23128569996993698}",
      "hasCurveFrom": true,
      "hasCurveTo": true,
      "point": "{0.98950738040192066, 0.23168654173764927}"
    },
    {
      "_class": "curvePoint",
      "cornerRadius": 0,
      "curveFrom": "{0.98822692512893462, 0.23569495941477123}",
      "curveMode": 4,
      "curveTo": "{0.98893828916948257, 0.23409159234392252}",
      "hasCurveFrom": true,
      "hasCurveTo": true,
      "point": "{0.98851147074515378, 0.23489327587934664}"
    },
    {
      "_class": "curvePoint",
      "cornerRadius": 0,
      "curveFrom": "{0.98737328828027726, 0.23850085178875677}",
      "curveMode": 2,
      "curveTo": "{0.98794237951271557, 0.23689748471790761}",
      "hasCurveFrom": true,
      "hasCurveTo": true,
      "point": "{0.98765783389649642, 0.2376991682533322}"
    },
    {
      "_class": "curvePoint",
      "cornerRadius": 0,
      "curveFrom": "{0.98623510581540097, 0.24170758593045416}",
      "curveMode": 2,
      "curveTo": "{0.98708874266405822, 0.23930253532418089}",
      "hasCurveFrom": true,
      "hasCurveTo": true,
      "point": "{0.98680419704783906, 0.24010421885960545}"
    },
    {
      "_class": "curvePoint",
      "cornerRadius": 0,
      "curveFrom": "{0.98509692335052446, 0.24531516183986382}",
      "curveMode": 4,
      "curveTo": "{0.98566601458296277, 0.24371179476901514}",
      "hasCurveFrom": false,
      "hasCurveTo": true,
      "point": "{0.98509692335052446, 0.24531516183986382}"
    },
    {
      "_class": "curvePoint",
      "cornerRadius": 0,
      "curveFrom": "{0.71264449582073597, 1.0141296723118547}",
      "curveMode": 4,
      "curveTo": "{0.73270496176418254, 0.95761098306443559}",
      "hasCurveFrom": true,
      "hasCurveTo": false,
      "point": "{0.73270496176418254, 0.95761098306443559}"
    },
    {
      "_class": "curvePoint",
      "cornerRadius": 0,
      "curveFrom": "{0.66028810243642166, 0.95761098306443559}",
      "curveMode": 4,
      "curveTo": "{0.68020629557175871, 1.0141296723118547}",
      "hasCurveFrom": false,
      "hasCurveTo": true,
      "point": "{0.66028810243642166, 0.95761098306443559}"
    },
    {
      "_class": "curvePoint",
      "cornerRadius": 0,
      "curveFrom": "{0.64022763649297509, 0.9010922938170155}",
      "curveMode": 4,
      "curveTo": "{0.66028810243642166, 0.95761098306443559}",
      "hasCurveFrom": true,
      "hasCurveTo": false,
      "point": "{0.66028810243642166, 0.95761098306443559}"
    },
    {
      "_class": "curvePoint",
      "cornerRadius": 0,
      "curveFrom": "{0.66028810243642166, 0.75358252329892772}",
      "curveMode": 4,
      "curveTo": "{0.64022763649297509, 0.8097003707786351}",
      "hasCurveFrom": false,
      "hasCurveTo": true,
      "point": "{0.66028810243642166, 0.75358252329892772}"
    },
    {
      "_class": "curvePoint",
      "cornerRadius": 0,
      "curveFrom": "{0.82532455984349973, 0.288606072752781}",
      "curveMode": 1,
      "curveTo": "{0.82532455984349973, 0.288606072752781}",
      "hasCurveFrom": false,
      "hasCurveTo": false,
      "point": "{0.82532455984349973, 0.288606072752781}"
    },
    {
      "_class": "curvePoint",
      "cornerRadius": 0,
      "curveFrom": "{0.022905922105637546, 0.288606072752781}",
      "curveMode": 4,
      "curveTo": "{0.051218210919438005, 0.288606072752781}",
      "hasCurveFrom": true,
      "hasCurveTo": false,
      "point": "{0.051218210919438005, 0.288606072752781}"
    },
    {
      "_class": "curvePoint",
      "cornerRadius": 0,
      "curveFrom": "{0, 0.14430303637639039}",
      "curveMode": 4,
      "curveTo": "{0, 0.22407054815111718}",
      "hasCurveFrom": false,
      "hasCurveTo": true,
      "point": "{0, 0.14430303637639039}"
    },
    {
      "_class": "curvePoint",
      "cornerRadius": 0,
      "curveFrom": "{0, 0.064535524601663563}",
      "curveMode": 4,
      "curveTo": "{0, 0.14430303637639039}",
      "hasCurveFrom": true,
      "hasCurveTo": false,
      "point": "{0, 0.14430303637639039}"
    },
    {
      "_class": "curvePoint",
      "cornerRadius": 0,
      "curveFrom": "{0.051218210919438005, 0}",
      "curveMode": 4,
      "curveTo": "{0.022905922105637546, 0}",
      "hasCurveFrom": false,
      "hasCurveTo": true,
      "point": "{0.051218210919438005, 0}"
    },
    {
      "_class": "curvePoint",
      "cornerRadius": 0,
      "curveFrom": "{0.94895963009069861, 0}",
      "curveMode": 4,
      "curveTo": "{0.94895963009069861, 0}",
      "hasCurveFrom": true,
      "hasCurveTo": false,
      "point": "{0.94895963009069861, 0}"
    },
    {
      "_class": "curvePoint",
      "cornerRadius": 0,
      "curveFrom": "{0.94981326693935597, 0}",
      "curveMode": 4,
      "curveTo": "{0.94895963009069861, 0}",
      "hasCurveFrom": true,
      "hasCurveTo": true,
      "point": "{0.94895963009069861, 0}"
    },
    {
      "_class": "curvePoint",
      "cornerRadius": 0,
      "curveFrom": "{0.95194735906099914, 0}",
      "curveMode": 2,
      "curveTo": "{0.95066690378801322, 0}",
      "hasCurveFrom": true,
      "hasCurveTo": true,
      "point": "{0.95152054063667046, 0}"
    }
  ],
  "resizingConstraint": 63,
  "resizingType": 0,
  "rotation": 0,
  "shouldBreakMaskChain": false
}