{
  "_class": "group",
  "booleanOperation": 0,
  "do_objectID": "43E6CF37-90D9-49EF-A336-06393553FD9A",
  "exportOptions": {
    "_class": "exportOptions",
    "do_objectID": "AA3BC54B-AAAE-45FB-B4E9-16DD211FDE1C",
    "exportFormats": [
    ],
    "includedLayerIds": [
    ],
    "layerOptions": 0,
    "shouldTrim": false
  },
  "frame": {
    "_class": "rect",
    "constrainProportions": false,
    "do_objectID": "BF0FE040-A35B-4B0F-AF85-097363F19DEC",
    "height": 22,
    "width": 21,
    "x": 1.5,
    "y": 1.5
  },
  "hasClickThrough": false,
  "isFixedToViewport": false,
  "isFlippedHorizontal": false,
  "isFlippedVertical": false,
  "isLocked": false,
  "isVisible": true,
  "layerListExpandedType": 0,
  "layers": [
    {
      "class": "shapeGroup",
      "id": "3CF32EC9-0D01-4B0C-B3A2-6B86C6AA7E83"
    }
  ],
  "name": "areachart",
  "nameIsFixed": false,
  "resizingConstraint": 63,
  "resizingType": 0,
  "rotation": 0,
  "shouldBreakMaskChain": false,
  "style": {
    "_class": "style",
    "do_objectID": "4381F1E8-FD4B-4A1B-821B-8F57ADA48BDE",
    "endMarkerType": 0,
    "miterLimit": 10,
    "startMarkerType": 0,
    "windingRule": 1
  }
}